repod-0.3.1.dist-info/METADATA
repod-0.3.1.dist-info/WHEEL
repod-0.3.1.dist-info/entry_points.txt
repod-0.3.1.dist-info/licenses/AUTHORS.rst
repod-0.3.1.dist-info/licenses/LICENSE
repod/__init__.py
repod/action/check.py
repod/action/task.py
repod/action/workflow.py
repod/archive/archive.py
repod/cli/__init__.py
repod/cli/argparse.py
repod/cli/cli.py
repod/commands.py
repod/common/enums.py
repod/common/models.py
repod/common/regex.py
repod/config/__init__.py
repod/config/defaults.py
repod/config/settings.py
repod/errors.py
repod/files/__init__.py
repod/files/buildinfo.py
repod/files/common.py
repod/files/mtree.py
repod/files/package.py
repod/files/pkginfo.py
repod/files/srcinfo.py
repod/py.typed
repod/repo/__init__.py
repod/repo/management/__init__.py
repod/repo/management/outputpackage.py
repod/repo/package/__init__.py
repod/repo/package/repofile.py
repod/repo/package/syncdb.py
repod/templates/desc_v1.j2
repod/templates/desc_v2.j2
repod/templates/files_v1.j2
repod/verification/__init__.py
repod/verification/pgp.py
repod/version/__init__.py
repod/version/alpm.py
repod/version/util.py
repod-0.3.1.dist-info/RECORD
