Metadata-Version: 2.1
Name: repod
Version: 0.3.1
Summary: Tooling to maintain binary package repositories for Linux distributions using the pacman package manager
Keywords: arch linux repository pacman packages
Home-page: https://gitlab.archlinux.org/archlinux/repod
Author-Email: Arch Linux <arch-projects@lists.archlinux.org>
License: GPL-3.0-or-later
Classifier: Development Status :: 3 - Alpha
Classifier: Environment :: Console
Classifier: Intended Audience :: End Users/Desktop
Classifier: License :: OSI Approved :: GNU General Public License v3 or later (GPLv3+)
Classifier: Natural Language :: English
Classifier: Operating System :: OS Independent
Classifier: Programming Language :: Python :: 3.10
Classifier: Topic :: Database
Classifier: Topic :: Database :: Database Engines/Servers
Classifier: Topic :: Documentation :: Sphinx
Classifier: Topic :: Internet
Classifier: Topic :: Security :: Cryptography
Classifier: Topic :: Software Development
Classifier: Topic :: System :: Archiving :: Packaging
Classifier: Topic :: System :: Operating System
Classifier: Topic :: System :: Software Distribution
Classifier: Topic :: Utilities
Classifier: Typing :: Typed
Project-URL: Bug tracker, https://gitlab.archlinux.org/archlinux/repod/-/issues/
Project-URL: Homepage, https://gitlab.archlinux.org/archlinux/repod
Project-URL: Repository, https://gitlab.archlinux.org/archlinux/repod
Project-URL: Documentation, https://repod.archlinux.page
Requires-Python: >=3.10
Requires-Dist: aiofiles>=23.2.1
Requires-Dist: email-validator>=2.1.0
Requires-Dist: jinja2>=3.1.3
Requires-Dist: orjson>=3.9.15
Requires-Dist: pydantic>=2.6.4
Requires-Dist: pydantic-settings>=2.2.1
Requires-Dist: python-magic>=0.4.27
Requires-Dist: pyxdg>=0.28
Requires-Dist: pyzstd>=0.15.10
Requires-Dist: subprocess-tee>=0.4.1
Requires-Dist: tomli>=2.0.1; python_version < "3.11"
Requires-Dist: pyalpm<1.0.0,>=0.10.6; extra == "alt-vercmp"
Requires-Dist: file-magic<1.0.0,>=0.4.0; extra == "alt-file"
Provides-Extra: alt_vercmp
Provides-Extra: alt_file
